{
  "schema_version": "v154",
  "event_id": "TASK-P0-CLOSED-0019",
  "parent_event_id": "TASK-P0-RESULT-0018",
  "task_id": "TASK-P0-0012",
  "event_time": "2026-04-01T10:00:00Z",
  "step_name": "P0.4",
  "actor_role": "AUDITOR",
  "event_type": "RESULT_ACCEPTED",
  "description": "P0.4 accepted. executor-runner.yml created and verified in main.",
  "status": "ACCEPTED",
  "next_actor_role": "ANALYST",
  "next_expected_event": "TASK_PROPOSED",
  "routing_decision_basis": "AUDITOR_POST_P0_4_RESULT_ACCEPTED",
  "commit_sha": "94a08052b797742d418225a2bccdf0b6e6742d29"
}
