{
  "schema_version": "v164",
  "task_id": "TASK-NEXT-FROM-BASELINE-0001",
  "step_name": "CONSOLIDATED-ARCHITECTURE-v3+v4+v5",
  "actor_role": "ANALYST",
  "event_type": "TASK_PROPOSED",
  "description": "Create consolidated architecture specification combining v3, v4, and v5 governance board designs with clear role separation, authority boundaries, and execution flow patterns",
  "status": "PROPOSED",
  "proof_target": "governance/consolidated_architecture_v345.md exists in main",
  "next_actor_role": "AUDITOR",
  "routing_decision_basis": "ROADMAP_ORDER_8_AFTER_DISCIPLINE_ENFORCEMENT_COMPLETED"
}
