{
  "checks": [
    "mediator_present",
    "source_auditor",
    "receiver_analyst",
    "proof_ref",
    "rule_version"
  ],
  "created_at": "2026-07-03T20:58:35Z",
  "github_run_attempt": "1",
  "github_run_id": "28683101798",
  "github_run_number": "396",
  "github_sha": "68134e471ae8d7aaec3daed6d8102f3712dd2913",
  "protocol": "BEM-931 v3.6",
  "receipt_type": "live_github_actions_horizontal_exchange",
  "registry": "governance/exchange/exchange_registry_v2.json",
  "roadmap_item": "RM-17",
  "status": "PASS",
  "workflow": "BEM-931 v3.6 Live Receipt Proof"
}
