{
  "checks": [
    "mediator_present",
    "source_auditor",
    "receiver_analyst",
    "proof_ref",
    "rule_version"
  ],
  "created_at": "2026-06-09T18:22:30Z",
  "github_run_attempt": "1",
  "github_run_id": "27226844437",
  "github_run_number": "23",
  "github_sha": "678b321b220ad8d2584eed88495b24939fc36153",
  "protocol": "BEM-931 v3.6",
  "receipt_type": "live_github_actions_horizontal_exchange",
  "registry": "governance/exchange/exchange_registry_v2.json",
  "roadmap_item": "RM-17",
  "status": "PASS",
  "workflow": "BEM-931 v3.6 Live Receipt Proof"
}
